{"impADt3qsEZP2TqDZNLzew==":"immochic-128x128.png","LfSV84Du5IRBkfypxEkkYg==":"2-2000x1500.jpg","NPfqvZG93J0DVXQCGp7IXg==":"3-2000x1500.jpg","xxqiX4A1OJ+7FPVqxyRmmA==":"big-2000x1332.jpg","w/yoBw5gFkZOZbGFEnpF8A==":"4-2000x1125.jpg","fWGuvLmii/04wZtUCmCS9A==":"immochic_retouche-1400x1400.png","N+JJKmskkku4pfYrZytPdQ==":"4-2000x1125.jpg","/uObDom2osjvWnfRwcjSNw==":"mbr-767x1080.jpg","++OBjkGh5ODpUPuop1ybaw==":"1398105907_nice_girls_14-700x464.jpg","jtrRh/YXtq+PUXm3TzIXSA==":"3ad1e566-3146-471a-9b0a-38866f15800d_rw-1920-1707x1280.jpg","TdICP62DGYdaFJ068NbTOw==":"7394568_120cc0a2-ca20-11e7-b6c4-76635f28ef58-1-1280x841.jpg","OGtRZVlRd5vVACNblLDfBg==":"index-289x175.jpg","qgb59CRkP01QQXYr8REZCQ==":"paris-parc-des-buttes-chaumont-1600x1060.jpg","ORc4wz1rlnBTyToNY1AlRQ==":"800px-mairie_de_paris_i-800x600.jpg","zWIiNtYtvA29pX7B1gWH0w==":"cuisine-laquee-noire-cuisine-cuisine-beautiful-cuisine-contemporary-design-trends-cuisine-cuisine-cuisine-laquee-noire-mat-824x618.jpg","hOXWQu8PW6Wvovjh7E7P/w==":"cabine-de-douche-hammam-flora-1000-800x800.jpg","PUVHPaziHk9MzH2t2L5T3g==":"00417ce6-800x533.jpg","sun95GyP37aQI+kgkmmkQA==":"ch1-1345x550.jpg","qycY/X5tUEbjM/j6tOrOFA==":"ch2-1345x550.jpg","ePlgPWSliYlMaZtZzxPuRg==":"cui1-1345x550.jpg","eZODA/KtB/4yswUI70N9+A==":"salon1-1345x550.jpg","nBZOktVyyFYTw9GbFdZS4A==":"tv-1345x550.jpg","2qXOElJ6ocdtzYNJg5h1OQ==":"tv-1-1345x550.jpg","3coxDO5toDDG28cOMFJkcQ==":"img-20190114-wa0016-768x1024.jpg","MTn0Fkp8VqJoUbcGluYbrA==":"img-20190114-wa0017-768x1024.jpg","NMQ349fwwaSnPhyaj+YAQg==":"img-20190114-wa0004-768x1024.jpg","5gdfrISdndTfNuNAHiyqlA==":"img-20190114-wa0012-768x1024.jpg","tjQVU5982iH+ZEC5zwT/Lw==":"img-20190114-wa0005-768x1024.jpg","2cOTFUmth2jLchk75pyVog==":"img-20190114-wa0009-768x1024.jpg","lcPpDziU5WCmS6A19hhvKA==":"img-20190114-wa0018-768x1024.jpg","3Bi8FFU3ihhD4P9CevzQVw==":"img-20190114-wa0019-768x1024.jpg","uCsEa+FmdShiqNthFo4Wog==":"img-20190114-wa0004-1-768x1024.jpg","VJHTi+F9Glt86WshyhzUkg==":"img-20190114-wa0005-1-768x1024.jpg","fvKJ7lsit0ELntsL0+w97g==":"img-20190114-wa0006-768x1024.jpg","Y1bSqCYL/MIROeixXWnjaw==":"img-20190114-wa0009-1-768x1024.jpg","PxW0tk0Jl3oyNp2Lm6h9Nw==":"img-20190114-wa0020-768x1024.jpg","XYJer3LZJ0NbmunMXjLFgA==":"img-20190114-wa0019-1-768x1024.jpg","Qn7T5gq6EFv8Ndf/Pu+muA==":"img-20190114-wa0021-768x1024.jpg","MDFyJOjZZtk60CNtnEVxAw==":"img-20190114-wa0012-1-768x1024.jpg","uNrgm/WHtEF6tt0KO6qo4w==":"img-20190114-wa0017-1-768x1024.jpg","CVh2jL/XBRXfcl/dBPUquA==":"img-20190114-wa0016-1-768x1024.jpg","Sf3m+G3r8eSyQRMK9yZNZQ==":"img-20190114-wa0015-768x1024.jpg","8WRIhLcYE5SpWqvuevTElw==":"img-20190114-wa0013-768x1024.jpg","Ly8Mob1udH3fKp3m4arFaQ==":"logo%20sab-128x128.png","gR8cZdwXhc0o1/T1tpYjTw==":"logo%20sab-128x128.png","kcS8BWFF9S9gHeGtvqQH4A==":"3ad1e566-3146-471a-9b0a-38866f15800d-rw-1920-1707x1280.jpg","s3FRLWYgaMai6QUZw8ezSA==":"dsc00738_979x734-979x734.jpg","O3Sjm/rPGIBk2PzpTJzD6Q==":"dsc00880_734x979-734x979.jpg","EUBdla47uflbefHBXrdrxw==":"dsc00880_734x979-734x979.jpeg","TdBqKvna2/5AIlK/KwkGUg==":"dsc00877_979x734-979x734.jpg","21Z5IKrIPVrCVjij0LqN/Q==":"beersheva_1148x823-1148x823.jpg","cajnlPp1+G7L3OxCCNQ+4A==":"dsc00852_979x734-979x734.jpg","mt+uwJXXnJSFu+nb/onSHg==":"dsc00738_979x734-979x734.jpeg","olR4mK8cFBoMsbCUPIzzwQ==":"beersheva_1148x823-1148x823.jpeg","/ivQRDlkRTo8UHu5e21+BA==":"dsc00697-979x734.jpeg","k43+A3rbkWDYFYYtU4mOhg==":"dsc00787-979x734.jpeg","acS+iOyyhOa1GBKGiq1+cQ==":"dsc00876-979x734.jpg","ps8H1bKRVu3zu3t05paAXw==":"beersheva-1148x823.jpg","WEQBCMnfThPDs6dY6hxmbg==":"chassidim-email-1600x1200.jpg","q1Oj0IX11bjgCKqgz+xAFA==":"dsc00866-734x979.jpg","r1JBDUFtXR0D6qgfwt0Vaw==":"still-life-with-red-vase-email-1175x1200.jpg","+fprAa4WYAgSzRICL4gR0Q==":"dsc00857-979x734.jpg","mDGYIebXq2Jk9zIHb1I6Lg==":"dsc00850-734x979.jpg","IkrSwxZhOAuLEa8otAHOWQ==":"eliyahu-and-elisha-email-1184x1200.jpg","VdBWU1eC4Fb+F5liC7ty3A==":"dsc00697-979x734.jpg","g15p0dIFykrHg00xM6qDuQ==":"skystructure-email-1252x1200.jpg","TOtwMIXMTwTbR6Q0rigYqQ==":"seder-pesach-email-1600x1200.jpg","CwiGRh6NUHAtQRApRu7qyA==":"jerusalemsunset-email-1266x1200.jpg","CfQgN8LL9ShaeeZ77tzu2g==":"gold-apples-1182x783.jpg","PT7Z5CdINwjf7M3Qp/njJg==":"screenshot-5.jpg","iPFoOveo9CkthBSLJ86jMA==":"beersheva-1148x823-800x574.jpg","GCzAb/R1QUN/9NJqKIZsPw==":"1.jpg","ce4mjBA0brbMD0XBcylfoQ==":"2.jpg","f+uSJ+kyKmB59a9+7a2W1w==":"4.jpg","6Yt3meNmTgX/At32ugq57Q==":"3.jpg","H8TIOkngZl9fCZfmviknAA==":"1-1.jpg","OZ48A6bStQwGuWwGNJagEQ==":"screenshot-1.jpg","+ZTsdj3gc6CxIZjsMlexpw==":"5.jpg"}